setup.py
dist_ex5/Binomialdistribution.py
dist_ex5/Gaussiandistribution.py
dist_ex5/Generaldistribution.py
dist_ex5/__init__.py
dist_ex5.egg-info/PKG-INFO
dist_ex5.egg-info/SOURCES.txt
dist_ex5.egg-info/dependency_links.txt
dist_ex5.egg-info/not-zip-safe
dist_ex5.egg-info/top_level.txt