Metadata-Version: 1.0
Name: dist-ex5
Version: 1.0
Summary: Gaussian and Binomial distributions
Home-page: UNKNOWN
Author: Amr Gharib
Author-email: amriagharib@gmail.com
License: UNKNOWN
Platform: UNKNOWN
